{"/about/":"https://students.iiserkol.ac.in/~rd17ms194/","/about.html":"https://students.iiserkol.ac.in/~rd17ms194/","/resume":"https://students.iiserkol.ac.in/~rd17ms194/cv/","/md/":"https://students.iiserkol.ac.in/~rd17ms194/markdown/","/markdown.html":"https://students.iiserkol.ac.in/~rd17ms194/markdown/","/nmp/":"https://students.iiserkol.ac.in/~rd17ms194/non-menu-page/","/nmp.html":"https://students.iiserkol.ac.in/~rd17ms194/non-menu-page/","/wordpress/blog-posts/":"https://students.iiserkol.ac.in/~rd17ms194/year-archive/"}